jointforces/__init__.py
jointforces/force.py
jointforces/growth.py
jointforces/materials.py
jointforces/mesh.py
jointforces/piv.py
jointforces/simulation.py
jointforces/strain.py
jointforces/utils.py
jointforces-1.0.7.dist-info/LICENSE
jointforces-1.0.7.dist-info/METADATA
jointforces-1.0.7.dist-info/WHEEL
jointforces-1.0.7.dist-info/top_level.txt
jointforces-1.0.7.dist-info/RECORD
